kafka_event_hub/__init__.py
kafka_event_hub/admin/__init__.py
kafka_event_hub/admin/client.py
kafka_event_hub/config/__init__.py
kafka_event_hub/config/config_utility.py
kafka_event_hub/config/content_collector_config.py
kafka_event_hub/config/event_hub_config.py
kafka_event_hub/consumers/__init__.py
kafka_event_hub/consumers/base_consumer.py
kafka_event_hub/consumers/elastic/__init__.py
kafka_event_hub/consumers/elastic/elastic_consumers.py
kafka_event_hub/consumers/simple/__init__.py
kafka_event_hub/consumers/simple/simple_consumer.py
kafka_event_hub/producers/__init__.py
kafka_event_hub/producers/base_producer.py
kafka_event_hub/producers/data_preparation.py
kafka_event_hub/producers/deletions/__init__.py
kafka_event_hub/producers/deletions/deletions.py
kafka_event_hub/producers/elastic/__init__.py
kafka_event_hub/producers/elastic/elastic_producer.py
kafka_event_hub/producers/filePush/__init__.py
kafka_event_hub/producers/filePush/cleanup_nebis.py
kafka_event_hub/producers/filePush/filepush_nebis_kafka.py
kafka_event_hub/producers/files/__init__.py
kafka_event_hub/producers/files/line_producer.py
kafka_event_hub/producers/httpget/__init__.py
kafka_event_hub/producers/httpget/httpget.py
kafka_event_hub/producers/mongo/__init__.py
kafka_event_hub/producers/mongo/mongo.py
kafka_event_hub/producers/mongo/cleanup/__init__.py
kafka_event_hub/producers/mongo/cleanup/sourceCleanUp.py
kafka_event_hub/producers/oai/__init__.py
kafka_event_hub/producers/oai/oai_producer_file.py
kafka_event_hub/producers/oai/oai_producer_kafka.py
kafka_event_hub/producers/oai/oai_sickle_wrapper.py
kafka_event_hub/producers/simple/__init__.py
kafka_event_hub/producers/simple/simple_producer.py
kafka_event_hub/producers/sru/__init__.py
kafka_event_hub/producers/sru/sru_producer.py
kafka_event_hub/producers/webdav/__init__.py
kafka_event_hub/producers/webdav/rero_content_provider.py
kafka_event_hub/producers/webdav/webdav_kafka.py
kafka_event_hub/utility/__init__.py
swissbib_kafka_event_hub-2.2.0.dist-info/LICENSE
swissbib_kafka_event_hub-2.2.0.dist-info/METADATA
swissbib_kafka_event_hub-2.2.0.dist-info/WHEEL
swissbib_kafka_event_hub-2.2.0.dist-info/top_level.txt
swissbib_kafka_event_hub-2.2.0.dist-info/RECORD
