Metadata-Version: 2.1
Name: swissbib-kafka-event-hub
Version: 2.2.0
Summary: Swissbib Kafka Event Hub
Home-page: https://github.com/swissbib/kafka_event_hub
Author: Jonas Waeber
Author-email: jonas.waeber@unibas.ch
License: LICENSE
Keywords: kafka,swissbib,oai,mongodb
Platform: UNKNOWN
Classifier: Programming Language :: Python
Classifier: Programming Language :: Python :: 3
Classifier: Operating System :: OS Independent
Classifier: Development Status :: 3 - Alpha
Classifier: Intended Audience :: Developers
Classifier: Intended Audience :: Science/Research
Classifier: Topic :: Software Development :: Libraries :: Python Modules
Requires-Dist: kafka-python
Requires-Dist: PyYAML
Requires-Dist: Sickle
Requires-Dist: PyMongo
Requires-Dist: requests
Requires-Dist: simple-elastic
Requires-Dist: deepmerge
